Metadata-Version: 2.1
Name: johnsnowlabs-by-ckl
Version: 5.0.29
Summary: The John Snow Labs Library gives you access to all of John Snow Labs Enterprise And Open Source products in an easy and simple manner. Access 10000+ state-of-the-art NLP and OCR models for Finance, Legal and Medical domains. Easily scalable to Spark Cluster 
Home-page: https://www.johnsnowlabs.com/
Author: John Snow Labs
Author-email: christian@johnsnowlabs.com
License: UNKNOWN
Keywords: Spark NLP OCR Finance Legal Medical John Snow Labs
Platform: UNKNOWN
Classifier: Development Status :: 5 - Production/Stable
Classifier: Intended Audience :: Developers
Classifier: Topic :: Software Development :: Build Tools
Classifier: License :: OSI Approved :: Apache Software License
Classifier: Programming Language :: Python :: 3
Classifier: Programming Language :: Python :: 3.4
Classifier: Programming Language :: Python :: 3.5
Classifier: Programming Language :: Python :: 3.6
License-File: LICENSE
Requires-Dist: colorama
Requires-Dist: databricks-api
Requires-Dist: dataclasses
Requires-Dist: nlu-by-ckl (==5.0.0rc14)
Requires-Dist: numpy
Requires-Dist: pydantic (==1.10.11)
Requires-Dist: requests
Requires-Dist: spark-nlp-display (==4.1)
Requires-Dist: spark-nlp (==5.0.2)
